glassure/__init__.py
glassure/calc.py
glassure/configuration.py
glassure/fitting.py
glassure/methods.py
glassure/normalization.py
glassure/optimization.py
glassure/pattern.py
glassure/scattering_factors.py
glassure/soller_correction.py
glassure/transfer_function.py
glassure/transform.py
glassure/utility.py
glassure/data/atomic_weights.csv
glassure/data/references.txt
glassure/data/brown_hubbell/convert_incoherent.py
glassure/data/brown_hubbell/incoherent_scattering_intensities.csv
glassure/data/brown_hubbell/param_coherent_scattering_factors.csv
glassure/data/brown_hubbell/incoherent/Ac.dat
glassure/data/brown_hubbell/incoherent/Ag.dat
glassure/data/brown_hubbell/incoherent/Al.dat
glassure/data/brown_hubbell/incoherent/Am.dat
glassure/data/brown_hubbell/incoherent/Ar.dat
glassure/data/brown_hubbell/incoherent/As.dat
glassure/data/brown_hubbell/incoherent/At.dat
glassure/data/brown_hubbell/incoherent/Au.dat
glassure/data/brown_hubbell/incoherent/B.dat
glassure/data/brown_hubbell/incoherent/Ba.dat
glassure/data/brown_hubbell/incoherent/Be.dat
glassure/data/brown_hubbell/incoherent/Bi.dat
glassure/data/brown_hubbell/incoherent/Bk.dat
glassure/data/brown_hubbell/incoherent/Br.dat
glassure/data/brown_hubbell/incoherent/C.dat
glassure/data/brown_hubbell/incoherent/Ca.dat
glassure/data/brown_hubbell/incoherent/Cd.dat
glassure/data/brown_hubbell/incoherent/Ce.dat
glassure/data/brown_hubbell/incoherent/Cf.dat
glassure/data/brown_hubbell/incoherent/Cl.dat
glassure/data/brown_hubbell/incoherent/Cm.dat
glassure/data/brown_hubbell/incoherent/Co.dat
glassure/data/brown_hubbell/incoherent/Cr.dat
glassure/data/brown_hubbell/incoherent/Cs.dat
glassure/data/brown_hubbell/incoherent/Cu.dat
glassure/data/brown_hubbell/incoherent/Dy.dat
glassure/data/brown_hubbell/incoherent/Er.dat
glassure/data/brown_hubbell/incoherent/Es.dat
glassure/data/brown_hubbell/incoherent/Eu.dat
glassure/data/brown_hubbell/incoherent/F.dat
glassure/data/brown_hubbell/incoherent/Fe.dat
glassure-2.3.3.dist-info/METADATA
glassure-2.3.3.dist-info/WHEEL
glassure-2.3.3.dist-info/licenses/LICENSE
glassure-2.3.3.dist-info/RECORD
