Metadata-Version: 2.4
Name: glassure
Version: 2.3.3
Summary: API and GUI for analysis of X-ray total scattering data
Author-email: Clemens Prescher <clemens.prescher@gmail.com>
License: MIT
License-File: LICENSE
Classifier: Intended Audience :: Science/Research
Classifier: Operating System :: OS Independent
Classifier: Programming Language :: Python
Classifier: Topic :: Scientific/Engineering
Classifier: Topic :: Scientific/Engineering :: Chemistry
Classifier: Topic :: Scientific/Engineering :: Information Analysis
Classifier: Topic :: Scientific/Engineering :: Physics
Classifier: Topic :: Scientific/Engineering :: Visualization
Requires-Python: >=3.10
Requires-Dist: lmfit<2.0.0,>=1.2.0
Requires-Dist: numpy>=1.26.0
Requires-Dist: pandas<3.0.0,>=2.1.0
Requires-Dist: pydantic<3.0.0,>=2.7.1
Requires-Dist: scipy>=1.11.3
Requires-Dist: xraylib<5.0.0,>=4.1.5
Provides-Extra: dev
Requires-Dist: mock<6.0.0,>=5.0.1; extra == 'dev'
Requires-Dist: pytest-cov<5.0.0,>=4.1.0; extra == 'dev'
Requires-Dist: pytest<8.0.0,>=7.3.1; extra == 'dev'
Provides-Extra: docs
Requires-Dist: autodoc-pydantic<3.0.0,>=2.2.0; extra == 'docs'
Requires-Dist: jupyter<2.0.0,>=1.0.0; extra == 'docs'
Requires-Dist: matplotlib<4.0.0,>=3.7.2; extra == 'docs'
Requires-Dist: myst-parser<3.0.0,>=2.0.0; extra == 'docs'
Requires-Dist: nbsphinx<1.0.0,>=0.9.3; extra == 'docs'
Requires-Dist: sphinx-rtd-theme<2.0.0,>=1.3.0; extra == 'docs'
Requires-Dist: sphinx<8.0.0,>=7.2.5; extra == 'docs'
